simpleLanguageRecognizer.so
simple_language_recognizer-0.0.3.dist-info/RECORD
simple_language_recognizer-0.0.3.dist-info/WHEEL
simple_language_recognizer-0.0.3.dist-info/METADATA
