Metadata-Version: 2.2
Name: simple-language-recognizer
Version: 0.0.3
Summary: Package that recognizes the language of an input string from over 70 languages. The package is probabilistic as the words in the input string are sampled. 
Keywords: language,recognizer,recognizor,recognition,detector,detecter,language-detector,language-checker,language recognition,real time
Author-Email: John Goh <jkh.goh@gmail.com>
License: MIT
Classifier: Programming Language :: Python :: 3
Classifier: License :: OSI Approved :: MIT License
Classifier: Operating System :: OS Independent
Classifier: Development Status :: 3 - Alpha
Requires-Python: >=3.9
